public class DatabaseConnect
{
    static final String JDBC_DRIVER = "com.mysql.jdbc.Driver";
    static final String DB_URL = "jdbc:mysql://localhost/ryderdatabase";
    static final String USER = "root";
    static final String PASS = "";

    /* Error */
    public void executeInsertShift(java.util.Date workdate, String day, java.sql.Time starttime, java.sql.Time finishtime, double hours, int orders, double pay, String ryderid)
    {
        // Byte code:
        //   0: aconst_null
        //   1: astore 11
        //   3: aconst_null
        //   4: astore 12
        //   6: ldc 8
        //   8: invokestatic 30	java/lang/Class:forName	(Ljava/lang/String;)Ljava/lang/Class;
        //   11: pop
        //   12: getstatic 36	java/lang/System:out	Ljava/io/PrintStream;
        //   15: ldc 42
        //   17: invokevirtual 44	java/io/PrintStream:println	(Ljava/lang/String;)V
        //   20: ldc 11
        //   22: ldc 14
        //   24: ldc 17
        //   26: invokestatic 50	java/sql/DriverManager:getConnection	(Ljava/lang/String;Ljava/lang/String;Ljava/lang/String;)Ljava/sql/Connection;
        //   29: astore 11
        //   31: getstatic 36	java/lang/System:out	Ljava/io/PrintStream;
        //   34: ldc 56
        //   36: invokevirtual 44	java/io/PrintStream:println	(Ljava/lang/String;)V
        //   39: aload 11
        //   41: invokeinterface 58 1 0
        //   46: astore 13
        //   48: aload 11
        //   50: ldc 64
        //   52: invokeinterface 66 2 0
        //   57: astore 14
        //   59: aload 14
        //   61: iconst_1
        //   62: aload_1
        //   63: checkcast 70	java/sql/Date
        //   66: invokeinterface 72 3 0
        //   71: aload 14
        //   73: iconst_2
        //   74: aload_2
        //   75: invokeinterface 78 3 0
        //   80: aload 14
        //   82: iconst_3
        //   83: aload_3
        //   84: invokeinterface 82 3 0
        //   89: aload 14
        //   91: iconst_4
        //   92: aload 4
        //   94: invokeinterface 82 3 0
        //   99: aload 14
        //   101: iconst_5
        //   102: dload 5
        //   104: invokeinterface 86 4 0
        //   109: aload 14
        //   111: bipush 6
        //   113: iload 7
        //   115: invokeinterface 90 3 0
        //   120: aload 14
        //   122: bipush 7
        //   124: dload 8
        //   126: invokeinterface 86 4 0
        //   131: aload 14
        //   133: bipush 8
        //   135: aload 10
        //   137: invokeinterface 78 3 0
        //   142: aload 14
        //   144: invokeinterface 94 1 0
        //   149: pop
        //   150: aload 13
        //   152: invokeinterface 98 1 0
        //   157: aload 11
        //   159: invokeinterface 103 1 0
        //   164: goto +145 -> 309
        //   167: astore 13
        //   169: aload 13
        //   171: invokevirtual 104	java/sql/SQLException:printStackTrace	()V
        //   174: aload 12
        //   176: ifnull +15 -> 191
        //   179: aload 12
        //   181: invokeinterface 98 1 0
        //   186: goto +5 -> 191
        //   189: astore 16
        //   191: aload 11
        //   193: ifnull +155 -> 348
        //   196: aload 11
        //   198: invokeinterface 103 1 0
        //   203: goto +145 -> 348
        //   206: astore 16
        //   208: aload 16
        //   210: invokevirtual 104	java/sql/SQLException:printStackTrace	()V
        //   213: goto +135 -> 348
        //   216: astore 13
        //   218: aload 13
        //   220: invokevirtual 109	java/lang/Exception:printStackTrace	()V
        //   223: aload 12
        //   225: ifnull +15 -> 240
        //   228: aload 12
        //   230: invokeinterface 98 1 0
        //   235: goto +5 -> 240
        //   238: astore 16
        //   240: aload 11
        //   242: ifnull +106 -> 348
        //   245: aload 11
        //   247: invokeinterface 103 1 0
        //   252: goto +96 -> 348
        //   255: astore 16
        //   257: aload 16
        //   259: invokevirtual 104	java/sql/SQLException:printStackTrace	()V
        //   262: goto +86 -> 348
        //   265: astore 15
        //   267: aload 12
        //   269: ifnull +15 -> 284
        //   272: aload 12
        //   274: invokeinterface 98 1 0
        //   279: goto +5 -> 284
        //   282: astore 16
        //   284: aload 11
        //   286: ifnull +20 -> 306
        //   289: aload 11
        //   291: invokeinterface 103 1 0
        //   296: goto +10 -> 306
        //   299: astore 16
        //   301: aload 16
        //   303: invokevirtual 104	java/sql/SQLException:printStackTrace	()V
        //   306: aload 15
        //   308: athrow
        //   309: aload 12
        //   311: ifnull +15 -> 326
        //   314: aload 12
        //   316: invokeinterface 98 1 0
        //   321: goto +5 -> 326
        //   324: astore 16
        //   326: aload 11
        //   328: ifnull +20 -> 348
        //   331: aload 11
        //   333: invokeinterface 103 1 0
        //   338: goto +10 -> 348
        //   341: astore 16
        //   343: aload 16
        //   345: invokevirtual 104	java/sql/SQLException:printStackTrace	()V
        //   348: getstatic 36	java/lang/System:out	Ljava/io/PrintStream;
        //   351: ldc 112
        //   353: invokevirtual 44	java/io/PrintStream:println	(Ljava/lang/String;)V
        //   356: return
        // Line number table:
        //   Java source line #16	-> byte code offset #0
        //   Java source line #17	-> byte code offset #3
        //   Java source line #21	-> byte code offset #6
        //   Java source line #24	-> byte code offset #12
        //   Java source line #25	-> byte code offset #20
        //   Java source line #28	-> byte code offset #31
        //   Java source line #30	-> byte code offset #39
        //   Java source line #36	-> byte code offset #48
        //   Java source line #37	-> byte code offset #59
        //   Java source line #38	-> byte code offset #71
        //   Java source line #39	-> byte code offset #80
        //   Java source line #40	-> byte code offset #89
        //   Java source line #41	-> byte code offset #99
        //   Java source line #42	-> byte code offset #109
        //   Java source line #43	-> byte code offset #120
        //   Java source line #44	-> byte code offset #131
        //   Java source line #45	-> byte code offset #142
        //   Java source line #48	-> byte code offset #150
        //   Java source line #49	-> byte code offset #157
        //   Java source line #50	-> byte code offset #164
        //   Java source line #52	-> byte code offset #169
        //   Java source line #59	-> byte code offset #174
        //   Java source line #60	-> byte code offset #179
        //   Java source line #61	-> byte code offset #186
        //   Java source line #64	-> byte code offset #191
        //   Java source line #65	-> byte code offset #196
        //   Java source line #66	-> byte code offset #203
        //   Java source line #67	-> byte code offset #208
        //   Java source line #53	-> byte code offset #216
        //   Java source line #55	-> byte code offset #218
        //   Java source line #59	-> byte code offset #223
        //   Java source line #60	-> byte code offset #228
        //   Java source line #61	-> byte code offset #235
        //   Java source line #64	-> byte code offset #240
        //   Java source line #65	-> byte code offset #245
        //   Java source line #66	-> byte code offset #252
        //   Java source line #67	-> byte code offset #257
        //   Java source line #56	-> byte code offset #265
        //   Java source line #59	-> byte code offset #267
        //   Java source line #60	-> byte code offset #272
        //   Java source line #61	-> byte code offset #279
        //   Java source line #64	-> byte code offset #284
        //   Java source line #65	-> byte code offset #289
        //   Java source line #66	-> byte code offset #296
        //   Java source line #67	-> byte code offset #301
        //   Java source line #69	-> byte code offset #306
        //   Java source line #59	-> byte code offset #309
        //   Java source line #60	-> byte code offset #314
        //   Java source line #61	-> byte code offset #321
        //   Java source line #64	-> byte code offset #326
        //   Java source line #65	-> byte code offset #331
        //   Java source line #66	-> byte code offset #338
        //   Java source line #67	-> byte code offset #343
        //   Java source line #70	-> byte code offset #348
        //   Java source line #71	-> byte code offset #356
        // Local variable table:
        //   start	length	slot	name	signature
        //   0	357	0	this	DatabaseConnect
        //   0	357	1	workdate	java.util.Date
        //   0	357	2	day	String
        //   0	357	3	starttime	java.sql.Time
        //   0	357	4	finishtime	java.sql.Time
        //   0	357	5	hours	double
        //   0	357	7	orders	int
        //   0	357	8	pay	double
        //   0	357	10	ryderid	String
        //   1	331	11	conn	java.sql.Connection
        //   4	311	12	stmt	java.sql.Statement
        //   46	105	13	statement	java.sql.Statement
        //   167	3	13	se	java.sql.SQLException
        //   216	3	13	e	Exception
        //   57	86	14	pstmt	java.sql.PreparedStatement
        //   265	42	15	localObject	Object
        //   189	1	16	localSQLException1	java.sql.SQLException
        //   206	3	16	se	java.sql.SQLException
        //   238	1	16	localSQLException2	java.sql.SQLException
        //   255	3	16	se	java.sql.SQLException
        //   282	1	16	localSQLException3	java.sql.SQLException
        //   299	3	16	se	java.sql.SQLException
        //   324	1	16	localSQLException4	java.sql.SQLException
        //   341	3	16	se	java.sql.SQLException
        // Exception table:
        //   from	to	target	type
        //   6	164	167	java/sql/SQLException
        //   174	186	189	java/sql/SQLException
        //   191	203	206	java/sql/SQLException
        //   6	164	216	java/lang/Exception
        //   223	235	238	java/sql/SQLException
        //   240	252	255	java/sql/SQLException
        //   6	174	265	finally
        //   216	223	265	finally
        //   267	279	282	java/sql/SQLException
        //   284	296	299	java/sql/SQLException
        //   309	321	324	java/sql/SQLException
        //   326	338	341	java/sql/SQLException
    }

    /* Error */
    public void executeDisplay()
    {
        // Byte code:
        //   0: aconst_null
        //   1: astore_1
        //   2: aconst_null
        //   3: astore_2
        //   4: ldc 8
        //   6: invokestatic 30	java/lang/Class:forName	(Ljava/lang/String;)Ljava/lang/Class;
        //   9: pop
        //   10: getstatic 36	java/lang/System:out	Ljava/io/PrintStream;
        //   13: ldc 42
        //   15: invokevirtual 44	java/io/PrintStream:println	(Ljava/lang/String;)V
        //   18: ldc 11
        //   20: ldc 14
        //   22: ldc 17
        //   24: invokestatic 50	java/sql/DriverManager:getConnection	(Ljava/lang/String;Ljava/lang/String;Ljava/lang/String;)Ljava/sql/Connection;
        //   27: astore_1
        //   28: getstatic 36	java/lang/System:out	Ljava/io/PrintStream;
        //   31: ldc 56
        //   33: invokevirtual 44	java/io/PrintStream:println	(Ljava/lang/String;)V
        //   36: aload_1
        //   37: invokeinterface 58 1 0
        //   42: astore_2
        //   43: ldc -109
        //   45: astore_3
        //   46: aload_2
        //   47: aload_3
        //   48: invokeinterface 149 2 0
        //   53: astore 4
        //   55: aload_1
        //   56: invokeinterface 58 1 0
        //   61: astore 5
        //   63: aload 5
        //   65: aload_3
        //   66: invokeinterface 149 2 0
        //   71: astore 6
        //   73: aload 6
        //   75: invokeinterface 153 1 0
        //   80: astore 7
        //   82: aload 7
        //   84: invokeinterface 159 1 0
        //   89: istore 8
        //   91: iconst_1
        //   92: istore 9
        //   94: goto +31 -> 125
        //   97: getstatic 36	java/lang/System:out	Ljava/io/PrintStream;
        //   100: ldc -92
        //   102: iconst_1
        //   103: anewarray 3	java/lang/Object
        //   106: dup
        //   107: iconst_0
        //   108: aload 7
        //   110: iload 9
        //   112: invokeinterface 166 2 0
        //   117: aastore
        //   118: invokevirtual 170	java/io/PrintStream:printf	(Ljava/lang/String;[Ljava/lang/Object;)Ljava/io/PrintStream;
        //   121: pop
        //   122: iinc 9 1
        //   125: iload 9
        //   127: iload 8
        //   129: if_icmple -32 -> 97
        //   132: getstatic 36	java/lang/System:out	Ljava/io/PrintStream;
        //   135: invokevirtual 174	java/io/PrintStream:println	()V
        //   138: goto +50 -> 188
        //   141: iconst_1
        //   142: istore 9
        //   144: goto +31 -> 175
        //   147: getstatic 36	java/lang/System:out	Ljava/io/PrintStream;
        //   150: ldc -92
        //   152: iconst_1
        //   153: anewarray 3	java/lang/Object
        //   156: dup
        //   157: iconst_0
        //   158: aload 6
        //   160: iload 9
        //   162: invokeinterface 176 2 0
        //   167: aastore
        //   168: invokevirtual 170	java/io/PrintStream:printf	(Ljava/lang/String;[Ljava/lang/Object;)Ljava/io/PrintStream;
        //   171: pop
        //   172: iinc 9 1
        //   175: iload 9
        //   177: iload 8
        //   179: if_icmple -32 -> 147
        //   182: getstatic 36	java/lang/System:out	Ljava/io/PrintStream;
        //   185: invokevirtual 174	java/io/PrintStream:println	()V
        //   188: aload 6
        //   190: invokeinterface 180 1 0
        //   195: ifne -54 -> 141
        //   198: aload 4
        //   200: invokeinterface 184 1 0
        //   205: aload_2
        //   206: invokeinterface 98 1 0
        //   211: aload_1
        //   212: invokeinterface 103 1 0
        //   217: goto +129 -> 346
        //   220: astore_3
        //   221: aload_3
        //   222: invokevirtual 104	java/sql/SQLException:printStackTrace	()V
        //   225: aload_2
        //   226: ifnull +14 -> 240
        //   229: aload_2
        //   230: invokeinterface 98 1 0
        //   235: goto +5 -> 240
        //   238: astore 11
        //   240: aload_1
        //   241: ifnull +140 -> 381
        //   244: aload_1
        //   245: invokeinterface 103 1 0
        //   250: goto +131 -> 381
        //   253: astore 11
        //   255: aload 11
        //   257: invokevirtual 104	java/sql/SQLException:printStackTrace	()V
        //   260: goto +121 -> 381
        //   263: astore_3
        //   264: aload_3
        //   265: invokevirtual 109	java/lang/Exception:printStackTrace	()V
        //   268: aload_2
        //   269: ifnull +14 -> 283
        //   272: aload_2
        //   273: invokeinterface 98 1 0
        //   278: goto +5 -> 283
        //   281: astore 11
        //   283: aload_1
        //   284: ifnull +97 -> 381
        //   287: aload_1
        //   288: invokeinterface 103 1 0
        //   293: goto +88 -> 381
        //   296: astore 11
        //   298: aload 11
        //   300: invokevirtual 104	java/sql/SQLException:printStackTrace	()V
        //   303: goto +78 -> 381
        //   306: astore 10
        //   308: aload_2
        //   309: ifnull +14 -> 323
        //   312: aload_2
        //   313: invokeinterface 98 1 0
        //   318: goto +5 -> 323
        //   321: astore 11
        //   323: aload_1
        //   324: ifnull +19 -> 343
        //   327: aload_1
        //   328: invokeinterface 103 1 0
        //   333: goto +10 -> 343
        //   336: astore 11
        //   338: aload 11
        //   340: invokevirtual 104	java/sql/SQLException:printStackTrace	()V
        //   343: aload 10
        //   345: athrow
        //   346: aload_2
        //   347: ifnull +14 -> 361
        //   350: aload_2
        //   351: invokeinterface 98 1 0
        //   356: goto +5 -> 361
        //   359: astore 11
        //   361: aload_1
        //   362: ifnull +19 -> 381
        //   365: aload_1
        //   366: invokeinterface 103 1 0
        //   371: goto +10 -> 381
        //   374: astore 11
        //   376: aload 11
        //   378: invokevirtual 104	java/sql/SQLException:printStackTrace	()V
        //   381: getstatic 36	java/lang/System:out	Ljava/io/PrintStream;
        //   384: ldc 112
        //   386: invokevirtual 44	java/io/PrintStream:println	(Ljava/lang/String;)V
        //   389: return
        // Line number table:
        //   Java source line #75	-> byte code offset #0
        //   Java source line #76	-> byte code offset #2
        //   Java source line #80	-> byte code offset #4
        //   Java source line #83	-> byte code offset #10
        //   Java source line #84	-> byte code offset #18
        //   Java source line #87	-> byte code offset #28
        //   Java source line #88	-> byte code offset #36
        //   Java source line #90	-> byte code offset #43
        //   Java source line #91	-> byte code offset #46
        //   Java source line #93	-> byte code offset #55
        //   Java source line #96	-> byte code offset #63
        //   Java source line #98	-> byte code offset #73
        //   Java source line #99	-> byte code offset #82
        //   Java source line #102	-> byte code offset #91
        //   Java source line #103	-> byte code offset #97
        //   Java source line #102	-> byte code offset #122
        //   Java source line #105	-> byte code offset #132
        //   Java source line #108	-> byte code offset #138
        //   Java source line #109	-> byte code offset #141
        //   Java source line #110	-> byte code offset #147
        //   Java source line #109	-> byte code offset #172
        //   Java source line #112	-> byte code offset #182
        //   Java source line #108	-> byte code offset #188
        //   Java source line #116	-> byte code offset #198
        //   Java source line #117	-> byte code offset #205
        //   Java source line #118	-> byte code offset #211
        //   Java source line #119	-> byte code offset #217
        //   Java source line #121	-> byte code offset #221
        //   Java source line #128	-> byte code offset #225
        //   Java source line #129	-> byte code offset #229
        //   Java source line #130	-> byte code offset #235
        //   Java source line #133	-> byte code offset #240
        //   Java source line #134	-> byte code offset #244
        //   Java source line #135	-> byte code offset #250
        //   Java source line #136	-> byte code offset #255
        //   Java source line #122	-> byte code offset #263
        //   Java source line #124	-> byte code offset #264
        //   Java source line #128	-> byte code offset #268
        //   Java source line #129	-> byte code offset #272
        //   Java source line #130	-> byte code offset #278
        //   Java source line #133	-> byte code offset #283
        //   Java source line #134	-> byte code offset #287
        //   Java source line #135	-> byte code offset #293
        //   Java source line #136	-> byte code offset #298
        //   Java source line #125	-> byte code offset #306
        //   Java source line #128	-> byte code offset #308
        //   Java source line #129	-> byte code offset #312
        //   Java source line #130	-> byte code offset #318
        //   Java source line #133	-> byte code offset #323
        //   Java source line #134	-> byte code offset #327
        //   Java source line #135	-> byte code offset #333
        //   Java source line #136	-> byte code offset #338
        //   Java source line #138	-> byte code offset #343
        //   Java source line #128	-> byte code offset #346
        //   Java source line #129	-> byte code offset #350
        //   Java source line #130	-> byte code offset #356
        //   Java source line #133	-> byte code offset #361
        //   Java source line #134	-> byte code offset #365
        //   Java source line #135	-> byte code offset #371
        //   Java source line #136	-> byte code offset #376
        //   Java source line #139	-> byte code offset #381
        //   Java source line #140	-> byte code offset #389
        // Local variable table:
        //   start	length	slot	name	signature
        //   0	390	0	this	DatabaseConnect
        //   1	365	1	conn	java.sql.Connection
        //   3	348	2	stmt	java.sql.Statement
        //   45	21	3	sql	String
        //   220	2	3	se	java.sql.SQLException
        //   263	2	3	e	Exception
        //   53	146	4	rs	java.sql.ResultSet
        //   61	3	5	statement	java.sql.Statement
        //   71	118	6	result_set	java.sql.ResultSet
        //   80	29	7	meta_data	java.sql.ResultSetMetaData
        //   89	89	8	number_of_columns	int
        //   92	34	9	i	int
        //   142	34	9	i	int
        //   306	38	10	localObject	Object
        //   238	1	11	localSQLException1	java.sql.SQLException
        //   253	3	11	se	java.sql.SQLException
        //   281	1	11	localSQLException2	java.sql.SQLException
        //   296	3	11	se	java.sql.SQLException
        //   321	1	11	localSQLException3	java.sql.SQLException
        //   336	3	11	se	java.sql.SQLException
        //   359	1	11	localSQLException4	java.sql.SQLException
        //   374	3	11	se	java.sql.SQLException
        // Exception table:
        //   from	to	target	type
        //   4	217	220	java/sql/SQLException
        //   225	235	238	java/sql/SQLException
        //   240	250	253	java/sql/SQLException
        //   4	217	263	java/lang/Exception
        //   268	278	281	java/sql/SQLException
        //   283	293	296	java/sql/SQLException
        //   4	225	306	finally
        //   263	268	306	finally
        //   308	318	321	java/sql/SQLException
        //   323	333	336	java/sql/SQLException
        //   346	356	359	java/sql/SQLException
        //   361	371	374	java/sql/SQLException
    }

    /* Error */
    public void executeInsertInvoiceInfo(String ryderid, java.util.Date invoicedate, double hourlyfees, double dropfees, double adjustments, double tips, double total)
    {
        // Byte code:
        //   0: aconst_null
        //   1: astore 13
        //   3: aconst_null
        //   4: astore 14
        //   6: ldc 8
        //   8: invokestatic 30	java/lang/Class:forName	(Ljava/lang/String;)Ljava/lang/Class;
        //   11: pop
        //   12: getstatic 36	java/lang/System:out	Ljava/io/PrintStream;
        //   15: ldc 42
        //   17: invokevirtual 44	java/io/PrintStream:println	(Ljava/lang/String;)V
        //   20: ldc 11
        //   22: ldc 14
        //   24: ldc 17
        //   26: invokestatic 50	java/sql/DriverManager:getConnection	(Ljava/lang/String;Ljava/lang/String;Ljava/lang/String;)Ljava/sql/Connection;
        //   29: astore 13
        //   31: getstatic 36	java/lang/System:out	Ljava/io/PrintStream;
        //   34: ldc 56
        //   36: invokevirtual 44	java/io/PrintStream:println	(Ljava/lang/String;)V
        //   39: aload 13
        //   41: invokeinterface 58 1 0
        //   46: astore 15
        //   48: aload 13
        //   50: ldc -61
        //   52: invokeinterface 66 2 0
        //   57: astore 16
        //   59: aload 16
        //   61: iconst_1
        //   62: aload_2
        //   63: checkcast 70	java/sql/Date
        //   66: invokeinterface 72 3 0
        //   71: aload 16
        //   73: iconst_2
        //   74: aload_1
        //   75: invokeinterface 78 3 0
        //   80: aload 16
        //   82: iconst_3
        //   83: dload_3
        //   84: invokeinterface 86 4 0
        //   89: aload 16
        //   91: iconst_4
        //   92: dload 5
        //   94: invokeinterface 86 4 0
        //   99: aload 16
        //   101: iconst_5
        //   102: dload 7
        //   104: invokeinterface 86 4 0
        //   109: aload 16
        //   111: bipush 6
        //   113: dload 9
        //   115: invokeinterface 86 4 0
        //   120: aload 16
        //   122: bipush 7
        //   124: dload 11
        //   126: invokeinterface 86 4 0
        //   131: aload 16
        //   133: invokeinterface 94 1 0
        //   138: pop
        //   139: aload 15
        //   141: invokeinterface 98 1 0
        //   146: aload 13
        //   148: invokeinterface 103 1 0
        //   153: goto +145 -> 298
        //   156: astore 15
        //   158: aload 15
        //   160: invokevirtual 104	java/sql/SQLException:printStackTrace	()V
        //   163: aload 14
        //   165: ifnull +15 -> 180
        //   168: aload 14
        //   170: invokeinterface 98 1 0
        //   175: goto +5 -> 180
        //   178: astore 18
        //   180: aload 13
        //   182: ifnull +155 -> 337
        //   185: aload 13
        //   187: invokeinterface 103 1 0
        //   192: goto +145 -> 337
        //   195: astore 18
        //   197: aload 18
        //   199: invokevirtual 104	java/sql/SQLException:printStackTrace	()V
        //   202: goto +135 -> 337
        //   205: astore 15
        //   207: aload 15
        //   209: invokevirtual 109	java/lang/Exception:printStackTrace	()V
        //   212: aload 14
        //   214: ifnull +15 -> 229
        //   217: aload 14
        //   219: invokeinterface 98 1 0
        //   224: goto +5 -> 229
        //   227: astore 18
        //   229: aload 13
        //   231: ifnull +106 -> 337
        //   234: aload 13
        //   236: invokeinterface 103 1 0
        //   241: goto +96 -> 337
        //   244: astore 18
        //   246: aload 18
        //   248: invokevirtual 104	java/sql/SQLException:printStackTrace	()V
        //   251: goto +86 -> 337
        //   254: astore 17
        //   256: aload 14
        //   258: ifnull +15 -> 273
        //   261: aload 14
        //   263: invokeinterface 98 1 0
        //   268: goto +5 -> 273
        //   271: astore 18
        //   273: aload 13
        //   275: ifnull +20 -> 295
        //   278: aload 13
        //   280: invokeinterface 103 1 0
        //   285: goto +10 -> 295
        //   288: astore 18
        //   290: aload 18
        //   292: invokevirtual 104	java/sql/SQLException:printStackTrace	()V
        //   295: aload 17
        //   297: athrow
        //   298: aload 14
        //   300: ifnull +15 -> 315
        //   303: aload 14
        //   305: invokeinterface 98 1 0
        //   310: goto +5 -> 315
        //   313: astore 18
        //   315: aload 13
        //   317: ifnull +20 -> 337
        //   320: aload 13
        //   322: invokeinterface 103 1 0
        //   327: goto +10 -> 337
        //   330: astore 18
        //   332: aload 18
        //   334: invokevirtual 104	java/sql/SQLException:printStackTrace	()V
        //   337: getstatic 36	java/lang/System:out	Ljava/io/PrintStream;
        //   340: ldc 112
        //   342: invokevirtual 44	java/io/PrintStream:println	(Ljava/lang/String;)V
        //   345: return
        // Line number table:
        //   Java source line #145	-> byte code offset #0
        //   Java source line #146	-> byte code offset #3
        //   Java source line #150	-> byte code offset #6
        //   Java source line #153	-> byte code offset #12
        //   Java source line #154	-> byte code offset #20
        //   Java source line #157	-> byte code offset #31
        //   Java source line #159	-> byte code offset #39
        //   Java source line #162	-> byte code offset #48
        //   Java source line #163	-> byte code offset #59
        //   Java source line #164	-> byte code offset #71
        //   Java source line #165	-> byte code offset #80
        //   Java source line #166	-> byte code offset #89
        //   Java source line #167	-> byte code offset #99
        //   Java source line #168	-> byte code offset #109
        //   Java source line #169	-> byte code offset #120
        //   Java source line #170	-> byte code offset #131
        //   Java source line #173	-> byte code offset #139
        //   Java source line #174	-> byte code offset #146
        //   Java source line #175	-> byte code offset #153
        //   Java source line #177	-> byte code offset #158
        //   Java source line #184	-> byte code offset #163
        //   Java source line #185	-> byte code offset #168
        //   Java source line #186	-> byte code offset #175
        //   Java source line #189	-> byte code offset #180
        //   Java source line #190	-> byte code offset #185
        //   Java source line #191	-> byte code offset #192
        //   Java source line #192	-> byte code offset #197
        //   Java source line #178	-> byte code offset #205
        //   Java source line #180	-> byte code offset #207
        //   Java source line #184	-> byte code offset #212
        //   Java source line #185	-> byte code offset #217
        //   Java source line #186	-> byte code offset #224
        //   Java source line #189	-> byte code offset #229
        //   Java source line #190	-> byte code offset #234
        //   Java source line #191	-> byte code offset #241
        //   Java source line #192	-> byte code offset #246
        //   Java source line #181	-> byte code offset #254
        //   Java source line #184	-> byte code offset #256
        //   Java source line #185	-> byte code offset #261
        //   Java source line #186	-> byte code offset #268
        //   Java source line #189	-> byte code offset #273
        //   Java source line #190	-> byte code offset #278
        //   Java source line #191	-> byte code offset #285
        //   Java source line #192	-> byte code offset #290
        //   Java source line #194	-> byte code offset #295
        //   Java source line #184	-> byte code offset #298
        //   Java source line #185	-> byte code offset #303
        //   Java source line #186	-> byte code offset #310
        //   Java source line #189	-> byte code offset #315
        //   Java source line #190	-> byte code offset #320
        //   Java source line #191	-> byte code offset #327
        //   Java source line #192	-> byte code offset #332
        //   Java source line #195	-> byte code offset #337
        //   Java source line #196	-> byte code offset #345
        // Local variable table:
        //   start	length	slot	name	signature
        //   0	346	0	this	DatabaseConnect
        //   0	346	1	ryderid	String
        //   0	346	2	invoicedate	java.util.Date
        //   0	346	3	hourlyfees	double
        //   0	346	5	dropfees	double
        //   0	346	7	adjustments	double
        //   0	346	9	tips	double
        //   0	346	11	total	double
        //   1	320	13	conn	java.sql.Connection
        //   4	300	14	stmt	java.sql.Statement
        //   46	94	15	statement	java.sql.Statement
        //   156	3	15	se	java.sql.SQLException
        //   205	3	15	e	Exception
        //   57	75	16	pstmt	java.sql.PreparedStatement
        //   254	42	17	localObject	Object
        //   178	1	18	localSQLException1	java.sql.SQLException
        //   195	3	18	se	java.sql.SQLException
        //   227	1	18	localSQLException2	java.sql.SQLException
        //   244	3	18	se	java.sql.SQLException
        //   271	1	18	localSQLException3	java.sql.SQLException
        //   288	3	18	se	java.sql.SQLException
        //   313	1	18	localSQLException4	java.sql.SQLException
        //   330	3	18	se	java.sql.SQLException
        // Exception table:
        //   from	to	target	type
        //   6	153	156	java/sql/SQLException
        //   163	175	178	java/sql/SQLException
        //   180	192	195	java/sql/SQLException
        //   6	153	205	java/lang/Exception
        //   212	224	227	java/sql/SQLException
        //   229	241	244	java/sql/SQLException
        //   6	163	254	finally
        //   205	212	254	finally
        //   256	268	271	java/sql/SQLException
        //   273	285	288	java/sql/SQLException
        //   298	310	313	java/sql/SQLException
        //   315	327	330	java/sql/SQLException
    }

    /* Error */
    private void add_invoice_shift_info(String ryderid, java.util.Date invoicedate)
    {
        // Byte code:
        //   0: aconst_null
        //   1: astore_3
        //   2: aconst_null
        //   3: astore 4
        //   5: ldc 8
        //   7: invokestatic 30	java/lang/Class:forName	(Ljava/lang/String;)Ljava/lang/Class;
        //   10: pop
        //   11: getstatic 36	java/lang/System:out	Ljava/io/PrintStream;
        //   14: ldc 42
        //   16: invokevirtual 44	java/io/PrintStream:println	(Ljava/lang/String;)V
        //   19: ldc 11
        //   21: ldc 14
        //   23: ldc 17
        //   25: invokestatic 50	java/sql/DriverManager:getConnection	(Ljava/lang/String;Ljava/lang/String;Ljava/lang/String;)Ljava/sql/Connection;
        //   28: astore_3
        //   29: getstatic 36	java/lang/System:out	Ljava/io/PrintStream;
        //   32: ldc 56
        //   34: invokevirtual 44	java/io/PrintStream:println	(Ljava/lang/String;)V
        //   37: aload_3
        //   38: invokeinterface 58 1 0
        //   43: astore 4
        //   45: ldc -51
        //   47: astore 5
        //   49: aload 4
        //   51: aload 5
        //   53: invokeinterface 149 2 0
        //   58: astore 6
        //   60: aload_3
        //   61: invokeinterface 58 1 0
        //   66: astore 7
        //   68: aload 7
        //   70: aload 5
        //   72: invokeinterface 149 2 0
        //   77: astore 8
        //   79: aload 8
        //   81: invokeinterface 153 1 0
        //   86: astore 9
        //   88: aload 9
        //   90: invokeinterface 159 1 0
        //   95: istore 10
        //   97: iconst_1
        //   98: istore 11
        //   100: goto +31 -> 131
        //   103: getstatic 36	java/lang/System:out	Ljava/io/PrintStream;
        //   106: ldc -92
        //   108: iconst_1
        //   109: anewarray 3	java/lang/Object
        //   112: dup
        //   113: iconst_0
        //   114: aload 9
        //   116: iload 11
        //   118: invokeinterface 166 2 0
        //   123: aastore
        //   124: invokevirtual 170	java/io/PrintStream:printf	(Ljava/lang/String;[Ljava/lang/Object;)Ljava/io/PrintStream;
        //   127: pop
        //   128: iinc 11 1
        //   131: iload 11
        //   133: iload 10
        //   135: if_icmple -32 -> 103
        //   138: getstatic 36	java/lang/System:out	Ljava/io/PrintStream;
        //   141: invokevirtual 174	java/io/PrintStream:println	()V
        //   144: goto +50 -> 194
        //   147: iconst_1
        //   148: istore 11
        //   150: goto +31 -> 181
        //   153: getstatic 36	java/lang/System:out	Ljava/io/PrintStream;
        //   156: ldc -92
        //   158: iconst_1
        //   159: anewarray 3	java/lang/Object
        //   162: dup
        //   163: iconst_0
        //   164: aload 8
        //   166: iload 11
        //   168: invokeinterface 176 2 0
        //   173: aastore
        //   174: invokevirtual 170	java/io/PrintStream:printf	(Ljava/lang/String;[Ljava/lang/Object;)Ljava/io/PrintStream;
        //   177: pop
        //   178: iinc 11 1
        //   181: iload 11
        //   183: iload 10
        //   185: if_icmple -32 -> 153
        //   188: getstatic 36	java/lang/System:out	Ljava/io/PrintStream;
        //   191: invokevirtual 174	java/io/PrintStream:println	()V
        //   194: aload 8
        //   196: invokeinterface 180 1 0
        //   201: ifne -54 -> 147
        //   204: aload 6
        //   206: invokeinterface 184 1 0
        //   211: aload 4
        //   213: invokeinterface 98 1 0
        //   218: aload_3
        //   219: invokeinterface 103 1 0
        //   224: goto +139 -> 363
        //   227: astore 5
        //   229: aload 5
        //   231: invokevirtual 104	java/sql/SQLException:printStackTrace	()V
        //   234: aload 4
        //   236: ifnull +15 -> 251
        //   239: aload 4
        //   241: invokeinterface 98 1 0
        //   246: goto +5 -> 251
        //   249: astore 13
        //   251: aload_3
        //   252: ifnull +148 -> 400
        //   255: aload_3
        //   256: invokeinterface 103 1 0
        //   261: goto +139 -> 400
        //   264: astore 13
        //   266: aload 13
        //   268: invokevirtual 104	java/sql/SQLException:printStackTrace	()V
        //   271: goto +129 -> 400
        //   274: astore 5
        //   276: aload 5
        //   278: invokevirtual 109	java/lang/Exception:printStackTrace	()V
        //   281: aload 4
        //   283: ifnull +15 -> 298
        //   286: aload 4
        //   288: invokeinterface 98 1 0
        //   293: goto +5 -> 298
        //   296: astore 13
        //   298: aload_3
        //   299: ifnull +101 -> 400
        //   302: aload_3
        //   303: invokeinterface 103 1 0
        //   308: goto +92 -> 400
        //   311: astore 13
        //   313: aload 13
        //   315: invokevirtual 104	java/sql/SQLException:printStackTrace	()V
        //   318: goto +82 -> 400
        //   321: astore 12
        //   323: aload 4
        //   325: ifnull +15 -> 340
        //   328: aload 4
        //   330: invokeinterface 98 1 0
        //   335: goto +5 -> 340
        //   338: astore 13
        //   340: aload_3
        //   341: ifnull +19 -> 360
        //   344: aload_3
        //   345: invokeinterface 103 1 0
        //   350: goto +10 -> 360
        //   353: astore 13
        //   355: aload 13
        //   357: invokevirtual 104	java/sql/SQLException:printStackTrace	()V
        //   360: aload 12
        //   362: athrow
        //   363: aload 4
        //   365: ifnull +15 -> 380
        //   368: aload 4
        //   370: invokeinterface 98 1 0
        //   375: goto +5 -> 380
        //   378: astore 13
        //   380: aload_3
        //   381: ifnull +19 -> 400
        //   384: aload_3
        //   385: invokeinterface 103 1 0
        //   390: goto +10 -> 400
        //   393: astore 13
        //   395: aload 13
        //   397: invokevirtual 104	java/sql/SQLException:printStackTrace	()V
        //   400: getstatic 36	java/lang/System:out	Ljava/io/PrintStream;
        //   403: ldc 112
        //   405: invokevirtual 44	java/io/PrintStream:println	(Ljava/lang/String;)V
        //   408: return
        // Line number table:
        //   Java source line #199	-> byte code offset #0
        //   Java source line #200	-> byte code offset #2
        //   Java source line #204	-> byte code offset #5
        //   Java source line #207	-> byte code offset #11
        //   Java source line #208	-> byte code offset #19
        //   Java source line #211	-> byte code offset #29
        //   Java source line #212	-> byte code offset #37
        //   Java source line #214	-> byte code offset #45
        //   Java source line #215	-> byte code offset #49
        //   Java source line #217	-> byte code offset #60
        //   Java source line #220	-> byte code offset #68
        //   Java source line #222	-> byte code offset #79
        //   Java source line #223	-> byte code offset #88
        //   Java source line #226	-> byte code offset #97
        //   Java source line #227	-> byte code offset #103
        //   Java source line #226	-> byte code offset #128
        //   Java source line #229	-> byte code offset #138
        //   Java source line #232	-> byte code offset #144
        //   Java source line #233	-> byte code offset #147
        //   Java source line #234	-> byte code offset #153
        //   Java source line #233	-> byte code offset #178
        //   Java source line #236	-> byte code offset #188
        //   Java source line #232	-> byte code offset #194
        //   Java source line #240	-> byte code offset #204
        //   Java source line #241	-> byte code offset #211
        //   Java source line #242	-> byte code offset #218
        //   Java source line #243	-> byte code offset #224
        //   Java source line #245	-> byte code offset #229
        //   Java source line #252	-> byte code offset #234
        //   Java source line #253	-> byte code offset #239
        //   Java source line #254	-> byte code offset #246
        //   Java source line #257	-> byte code offset #251
        //   Java source line #258	-> byte code offset #255
        //   Java source line #259	-> byte code offset #261
        //   Java source line #260	-> byte code offset #266
        //   Java source line #246	-> byte code offset #274
        //   Java source line #248	-> byte code offset #276
        //   Java source line #252	-> byte code offset #281
        //   Java source line #253	-> byte code offset #286
        //   Java source line #254	-> byte code offset #293
        //   Java source line #257	-> byte code offset #298
        //   Java source line #258	-> byte code offset #302
        //   Java source line #259	-> byte code offset #308
        //   Java source line #260	-> byte code offset #313
        //   Java source line #249	-> byte code offset #321
        //   Java source line #252	-> byte code offset #323
        //   Java source line #253	-> byte code offset #328
        //   Java source line #254	-> byte code offset #335
        //   Java source line #257	-> byte code offset #340
        //   Java source line #258	-> byte code offset #344
        //   Java source line #259	-> byte code offset #350
        //   Java source line #260	-> byte code offset #355
        //   Java source line #262	-> byte code offset #360
        //   Java source line #252	-> byte code offset #363
        //   Java source line #253	-> byte code offset #368
        //   Java source line #254	-> byte code offset #375
        //   Java source line #257	-> byte code offset #380
        //   Java source line #258	-> byte code offset #384
        //   Java source line #259	-> byte code offset #390
        //   Java source line #260	-> byte code offset #395
        //   Java source line #263	-> byte code offset #400
        //   Java source line #264	-> byte code offset #408
        // Local variable table:
        //   start	length	slot	name	signature
        //   0	409	0	this	DatabaseConnect
        //   0	409	1	ryderid	String
        //   0	409	2	invoicedate	java.util.Date
        //   1	384	3	conn	java.sql.Connection
        //   3	366	4	stmt	java.sql.Statement
        //   47	24	5	sql	String
        //   227	3	5	se	java.sql.SQLException
        //   274	3	5	e	Exception
        //   58	147	6	rs	java.sql.ResultSet
        //   66	3	7	statement	java.sql.Statement
        //   77	118	8	result_set	java.sql.ResultSet
        //   86	29	9	meta_data	java.sql.ResultSetMetaData
        //   95	89	10	number_of_columns	int
        //   98	34	11	i	int
        //   148	34	11	i	int
        //   321	40	12	localObject	Object
        //   249	1	13	localSQLException1	java.sql.SQLException
        //   264	3	13	se	java.sql.SQLException
        //   296	1	13	localSQLException2	java.sql.SQLException
        //   311	3	13	se	java.sql.SQLException
        //   338	1	13	localSQLException3	java.sql.SQLException
        //   353	3	13	se	java.sql.SQLException
        //   378	1	13	localSQLException4	java.sql.SQLException
        //   393	3	13	se	java.sql.SQLException
        // Exception table:
        //   from	to	target	type
        //   5	224	227	java/sql/SQLException
        //   234	246	249	java/sql/SQLException
        //   251	261	264	java/sql/SQLException
        //   5	224	274	java/lang/Exception
        //   281	293	296	java/sql/SQLException
        //   298	308	311	java/sql/SQLException
        //   5	234	321	finally
        //   274	281	321	finally
        //   323	335	338	java/sql/SQLException
        //   340	350	353	java/sql/SQLException
        //   363	375	378	java/sql/SQLException
        //   380	390	393	java/sql/SQLException
    }
}
